NetStructer/__init__.py
NetStructer/const.py
NetStructer/modules.py
NetStructer/tools.py
NetStructer-2.9.5.dist-info/METADATA
NetStructer-2.9.5.dist-info/WHEEL
NetStructer-2.9.5.dist-info/top_level.txt
NetStructer-2.9.5.dist-info/RECORD
