Metadata-Version: 2.1
Name: NetStructer
Version: 2.9.5
Author: Haytam-Zakaria
Classifier: Programming Language :: Python :: 3
Classifier: Operating System :: OS Independent
Classifier: License :: OSI Approved :: MIT License
Requires-Dist: cryptography
Requires-Dist: psutil
Requires-Dist: requests
